colander_client/__init__.py
colander_client/client.py
colander_client/domain/__init__.py
colander_client/domain/artifact.py
colander_client/domain/base.py
colander_client/domain/case.py
colander_client/domain/device.py
colander_client/domain/observable.py
colander_client/domain/pirogue_experiment.py
colander_client/domain/relation.py
colander_client/domain/team.py
colander_client-1.0.5.dist-info/LICENSE.txt
colander_client-1.0.5.dist-info/METADATA
colander_client-1.0.5.dist-info/WHEEL
colander_client-1.0.5.dist-info/top_level.txt
colander_client-1.0.5.dist-info/RECORD
