Metadata-Version: 2.1
Name: colander-client
Version: 1.0.5
Summary: Colander REST API Python client
Home-page: https://github.com/PiRogueToolSuite/colander-python-client.git
Author: U+039b
Author-email: esther@pts-project.org
License: UNKNOWN
Platform: UNKNOWN
Classifier: Development Status :: 3 - Alpha
Classifier: License :: OSI Approved :: GNU Affero General Public License v3
Classifier: Natural Language :: English
Classifier: Topic :: Security
Classifier: Topic :: Software Development :: Libraries :: Python Modules
Classifier: Topic :: Utilities
Requires-Dist: coreapi
Requires-Dist: deprecated
